abhiprime/__init__.py
abhiprime-6.0.0.dist-info/LICENCE.txt
abhiprime-6.0.0.dist-info/METADATA
abhiprime-6.0.0.dist-info/WHEEL
abhiprime-6.0.0.dist-info/top_level.txt
abhiprime-6.0.0.dist-info/RECORD
