Metadata-Version: 2.1
Name: abhiprime
Version: 6.0.0
Summary: A program to check if the given number is a prime number or not
Home-page: UNKNOWN
Author: Abhishek Singh
Author-email: abhisheksingh@ggits.org
License: UNKNOWN
Keywords: primenumber
Platform: UNKNOWN
